relaxed_ik_core-0.1.4.dist-info/METADATA
relaxed_ik_core-0.1.4.dist-info/WHEEL
relaxed_ik_core-0.1.4.dist-info/license_files/LICENSE
relaxed_ik_lib/__init__.py
relaxed_ik_lib/relaxed_ik_lib.cpython-39-darwin.so
relaxed_ik_core-0.1.4.dist-info/RECORD
