Metadata-Version: 2.3
Name: relaxed_ik_core
Version: 0.1.4
Classifier: Programming Language :: Rust
Classifier: Programming Language :: Python :: Implementation :: CPython
Classifier: Programming Language :: Python :: Implementation :: PyPy
License-File: LICENSE
Summary: RangedIK is a real-time motion synthesis method that exploits range flexibility to satisfy multiple kinematic requirements.
Author: djrakita <djrakita@gmail.com>, yepw <yepingw@outlook.com>
Author-email: djrakita <djrakita@gmail.com>, yepw <yepingw@outlook.com>
Requires-Python: >=3.8
